chronulus/__init__.py
chronulus/environment.py
chronulus/io.py
chronulus/prediction.py
chronulus/session.py
chronulus/estimator/__init__.py
chronulus/estimator/base.py
chronulus/estimator/binary_predictor.py
chronulus/estimator/normalized_forecaster.py
chronulus/etc/__init__.py
chronulus/etc/default.env
chronulus/types/__init__.py
chronulus-0.0.14.dist-info/LICENSE
chronulus-0.0.14.dist-info/METADATA
chronulus-0.0.14.dist-info/WHEEL
chronulus-0.0.14.dist-info/top_level.txt
chronulus-0.0.14.dist-info/RECORD
