Metadata-Version: 2.1
Name: chronulus
Version: 0.0.14
Summary: Chronulus AI Python SDK
Author: Chronulus AI
Author-email: jeremy@chronulus.com
License: MIT
Classifier: Programming Language :: Python :: 3
Classifier: Programming Language :: Python :: 3.10
Classifier: Programming Language :: Python :: 3.11
Classifier: Programming Language :: Python :: 3.12
Classifier: License :: OSI Approved :: MIT License
License-File: LICENSE
Requires-Dist: chronulus-core>=0.0.23
Requires-Dist: pydantic<3.0.0,>=2.9.0
Requires-Dist: pydantic-settings<3.0.0,~=2.6.0
Requires-Dist: python-dotenv==1.0.1
